mytree/__init__.py
mytree/admin.py
mytree/apps.py
mytree/models.py
mytree/serializers.py
mytree/tests.py
mytree/urls.py
mytree/views.py
mytree/migrations/0001_initial.py
mytree/migrations/0002_tree.py
mytree/migrations/0003_remove_tree_root_tree_root_content_type_and_more.py
mytree/migrations/__init__.py
tree_control_app-1.0.2.dist-info/METADATA
tree_control_app-1.0.2.dist-info/WHEEL
tree_control_app-1.0.2.dist-info/top_level.txt
tree_control_app-1.0.2.dist-info/RECORD
